{
	"actions": [
		{
			"startTime": "300",
			"endTime": "600",
			"taskType": {
				"predefined": "Move"
			},
			"shuntingUnit": {
				"id": "0",
				"members": [
					{
						"id": "2401",
						"type": {
							"displayName": "SLT",
							"carriages": 4,
							"reversalDuration": "0",
							"length": 69.36,
							"combineDuration": "180",
							"splitDuration": "120",
							"backNormTime": "120",
							"backAdditionTime": "16"
						}
					}
				],
				"parentIDs": [],
				"childIDs": [],
				"standingType": ""
			},
			"location": "41",
			"resources": [
				{
					"name": "59",
					"trackPartId": "59"
				},
				{
					"name": "24",
					"trackPartId": "24"
				},
				{
					"name": "58",
					"trackPartId": "58"
				},
				{
					"name": "23",
					"trackPartId": "23"
				},
				{
					"name": "57",
					"trackPartId": "57"
				},
				{
					"name": "22",
					"trackPartId": "22"
				},
				{
					"name": "56",
					"trackPartId": "56"
				},
				{
					"name": "20",
					"trackPartId": "20"
				},
				{
					"name": "55",
					"trackPartId": "55"
				},
				{
					"name": "21",
					"trackPartId": "21"
				},
				{
					"name": "66",
					"trackPartId": "66"
				},
				{
					"name": "8",
					"trackPartId": "8"
				}
			],
			"trainUnitIds": []
		},
		{
			"startTime": "300",
			"endTime": "300",
			"taskType": {
				"predefined": "Arrive"
			},
			"shuntingUnit": {
				"id": "0",
				"members": [
					{
						"id": "2401",
						"type": {
							"displayName": "SLT",
							"carriages": 4,
							"reversalDuration": "0",
							"length": 69.36,
							"combineDuration": "180",
							"splitDuration": "120",
							"backNormTime": "120",
							"backAdditionTime": "16"
						}
					}
				],
				"parentIDs": [],
				"childIDs": [],
				"standingType": ""
			},
			"location": "47",
			"resources": [
				{
					"name": "41",
					"trackPartId": "41"
				}
			],
			"trainUnitIds": []
		},
		{
			"startTime": "600",
			"endTime": "600",
			"taskType": {
				"predefined": "Arrive"
			},
			"shuntingUnit": {
				"id": "1",
				"members": [
					{
						"id": "2402",
						"type": {
							"displayName": "SLT",
							"carriages": 4,
							"reversalDuration": "0",
							"length": 69.36,
							"combineDuration": "180",
							"splitDuration": "120",
							"backNormTime": "120",
							"backAdditionTime": "16"
						}
					},
					{
						"id": "2403",
						"type": {
							"displayName": "SLT",
							"carriages": 4,
							"reversalDuration": "0",
							"length": 69.36,
							"combineDuration": "180",
							"splitDuration": "120",
							"backNormTime": "120",
							"backAdditionTime": "16"
						}
					}
				],
				"parentIDs": [],
				"childIDs": [],
				"standingType": ""
			},
			"location": "47",
			"resources": [
				{
					"name": "41",
					"trackPartId": "41"
				}
			],
			"trainUnitIds": []
		},
		{
			"startTime": "900",
			"endTime": "900",
			"taskType": {
				"predefined": "Arrive"
			},
			"shuntingUnit": {
				"id": "2",
				"members": [
					{
						"id": "2404",
						"type": {
							"displayName": "SLT",
							"carriages": 4,
							"reversalDuration": "0",
							"length": 69.36,
							"combineDuration": "180",
							"splitDuration": "120",
							"backNormTime": "120",
							"backAdditionTime": "16"
						}
					}
				],
				"parentIDs": [],
				"childIDs": [],
				"standingType": ""
			},
			"location": "47",
			"resources": [
				{
					"name": "41",
					"trackPartId": "41"
				}
			],
			"trainUnitIds": []
		},
		{
			"startTime": "900",
			"endTime": "1170",
			"taskType": {
				"predefined": "Move"
			},
			"shuntingUnit": {
				"id": "0",
				"members": [
					{
						"id": "2401",
						"type": {
							"displayName": "SLT",
							"carriages": 4,
							"reversalDuration": "0",
							"length": 69.36,
							"combineDuration": "180",
							"splitDuration": "120",
							"backNormTime": "120",
							"backAdditionTime": "16"
						}
					}
				],
				"parentIDs": [],
				"childIDs": [],
				"standingType": ""
			},
			"location": "8",
			"resources": [
				{
					"name": "67",
					"trackPartId": "67"
				},
				{
					"name": "27",
					"trackPartId": "27"
				},
				{
					"name": "69",
					"trackPartId": "69"
				},
				{
					"name": "26",
					"trackPartId": "26"
				},
				{
					"name": "68",
					"trackPartId": "68"
				},
				{
					"name": "10",
					"trackPartId": "10"
				}
			],
			"trainUnitIds": []
		},
		{
			"startTime": "600",
			"endTime": "900",
			"taskType": {
				"predefined": "Wait"
			},
			"shuntingUnit": {
				"id": "0",
				"members": [
					{
						"id": "2401",
						"type": {
							"displayName": "SLT",
							"carriages": 4,
							"reversalDuration": "0",
							"length": 69.36,
							"combineDuration": "180",
							"splitDuration": "120",
							"backNormTime": "120",
							"backAdditionTime": "16"
						}
					}
				],
				"parentIDs": [],
				"childIDs": [],
				"standingType": ""
			},
			"location": "8",
			"resources": [],
			"trainUnitIds": []
		},
		{
			"startTime": "1770",
			"endTime": "2040",
			"taskType": {
				"predefined": "Move"
			},
			"shuntingUnit": {
				"id": "0",
				"members": [
					{
						"id": "2401",
						"type": {
							"displayName": "SLT",
							"carriages": 4,
							"reversalDuration": "0",
							"length": 69.36,
							"combineDuration": "180",
							"splitDuration": "120",
							"backNormTime": "120",
							"backAdditionTime": "16"
						}
					}
				],
				"parentIDs": [],
				"childIDs": [],
				"standingType": ""
			},
			"location": "10",
			"resources": [
				{
					"name": "68",
					"trackPartId": "68"
				},
				{
					"name": "32",
					"trackPartId": "32"
				},
				{
					"name": "49",
					"trackPartId": "49"
				},
				{
					"name": "33",
					"trackPartId": "33"
				},
				{
					"name": "69",
					"trackPartId": "69"
				},
				{
					"name": "27",
					"trackPartId": "27"
				},
				{
					"name": "67",
					"trackPartId": "67"
				},
				{
					"name": "8",
					"trackPartId": "8"
				}
			],
			"trainUnitIds": []
		},
		{
			"startTime": "1170",
			"endTime": "1770",
			"taskType": {
				"other": "Reinigingsperron"
			},
			"shuntingUnit": {
				"id": "0",
				"members": [
					{
						"id": "2401",
						"type": {
							"displayName": "SLT",
							"carriages": 4,
							"reversalDuration": "0",
							"length": 69.36,
							"combineDuration": "180",
							"splitDuration": "120",
							"backNormTime": "120",
							"backAdditionTime": "16"
						}
					}
				],
				"parentIDs": [],
				"childIDs": [],
				"standingType": ""
			},
			"location": "10",
			"resources": [
				{
					"name": "72",
					"facilityId": "72"
				}
			],
			"trainUnitIds": []
		},
		{
			"startTime": "2040",
			"endTime": "2580",
			"taskType": {
				"predefined": "Move"
			},
			"shuntingUnit": {
				"id": "1",
				"members": [
					{
						"id": "2402",
						"type": {
							"displayName": "SLT",
							"carriages": 4,
							"reversalDuration": "0",
							"length": 69.36,
							"combineDuration": "180",
							"splitDuration": "120",
							"backNormTime": "120",
							"backAdditionTime": "16"
						}
					},
					{
						"id": "2403",
						"type": {
							"displayName": "SLT",
							"carriages": 4,
							"reversalDuration": "0",
							"length": 69.36,
							"combineDuration": "180",
							"splitDuration": "120",
							"backNormTime": "120",
							"backAdditionTime": "16"
						}
					}
				],
				"parentIDs": [],
				"childIDs": [],
				"standingType": ""
			},
			"location": "41",
			"resources": [
				{
					"name": "59",
					"trackPartId": "59"
				},
				{
					"name": "24",
					"trackPartId": "24"
				},
				{
					"name": "58",
					"trackPartId": "58"
				},
				{
					"name": "23",
					"trackPartId": "23"
				},
				{
					"name": "57",
					"trackPartId": "57"
				},
				{
					"name": "22",
					"trackPartId": "22"
				},
				{
					"name": "56",
					"trackPartId": "56"
				},
				{
					"name": "20",
					"trackPartId": "20"
				},
				{
					"name": "55",
					"trackPartId": "55"
				},
				{
					"name": "21",
					"trackPartId": "21"
				},
				{
					"name": "66",
					"trackPartId": "66"
				},
				{
					"name": "31",
					"trackPartId": "31"
				},
				{
					"name": "65",
					"trackPartId": "65"
				},
				{
					"name": "30",
					"trackPartId": "30"
				},
				{
					"name": "64",
					"trackPartId": "64"
				},
				{
					"name": "7",
					"trackPartId": "7"
				},
				{
					"name": "69",
					"trackPartId": "69"
				},
				{
					"name": "26",
					"trackPartId": "26"
				},
				{
					"name": "68",
					"trackPartId": "68"
				},
				{
					"name": "10",
					"trackPartId": "10"
				}
			],
			"trainUnitIds": []
		},
		{
			"startTime": "600",
			"endTime": "2040",
			"taskType": {
				"predefined": "Wait"
			},
			"shuntingUnit": {
				"id": "1",
				"members": [
					{
						"id": "2402",
						"type": {
							"displayName": "SLT",
							"carriages": 4,
							"reversalDuration": "0",
							"length": 69.36,
							"combineDuration": "180",
							"splitDuration": "120",
							"backNormTime": "120",
							"backAdditionTime": "16"
						}
					},
					{
						"id": "2403",
						"type": {
							"displayName": "SLT",
							"carriages": 4,
							"reversalDuration": "0",
							"length": 69.36,
							"combineDuration": "180",
							"splitDuration": "120",
							"backNormTime": "120",
							"backAdditionTime": "16"
						}
					}
				],
				"parentIDs": [],
				"childIDs": [],
				"standingType": ""
			},
			"location": "41",
			"resources": [],
			"trainUnitIds": []
		},
		{
			"startTime": "2040",
			"endTime": "3300",
			"taskType": {
				"predefined": "Wait"
			},
			"shuntingUnit": {
				"id": "0",
				"members": [
					{
						"id": "2401",
						"type": {
							"displayName": "SLT",
							"carriages": 4,
							"reversalDuration": "0",
							"length": 69.36,
							"combineDuration": "180",
							"splitDuration": "120",
							"backNormTime": "120",
							"backAdditionTime": "16"
						}
					}
				],
				"parentIDs": [],
				"childIDs": [],
				"standingType": ""
			},
			"location": "8",
			"resources": [],
			"trainUnitIds": []
		},
		{
			"startTime": "3300",
			"endTime": "3600",
			"taskType": {
				"predefined": "Move"
			},
			"shuntingUnit": {
				"id": "0",
				"members": [
					{
						"id": "2401",
						"type": {
							"displayName": "SLT",
							"carriages": 4,
							"reversalDuration": "0",
							"length": 69.36,
							"combineDuration": "180",
							"splitDuration": "120",
							"backNormTime": "120",
							"backAdditionTime": "16"
						}
					}
				],
				"parentIDs": [],
				"childIDs": [],
				"standingType": ""
			},
			"location": "8",
			"resources": [
				{
					"name": "66",
					"trackPartId": "66"
				},
				{
					"name": "21",
					"trackPartId": "21"
				},
				{
					"name": "55",
					"trackPartId": "55"
				},
				{
					"name": "20",
					"trackPartId": "20"
				},
				{
					"name": "56",
					"trackPartId": "56"
				},
				{
					"name": "22",
					"trackPartId": "22"
				},
				{
					"name": "57",
					"trackPartId": "57"
				},
				{
					"name": "23",
					"trackPartId": "23"
				},
				{
					"name": "58",
					"trackPartId": "58"
				},
				{
					"name": "24",
					"trackPartId": "24"
				},
				{
					"name": "59",
					"trackPartId": "59"
				},
				{
					"name": "41",
					"trackPartId": "41"
				}
			],
			"trainUnitIds": []
		},
		{
			"startTime": "3600",
			"endTime": "3600",
			"taskType": {
				"predefined": "Exit"
			},
			"shuntingUnit": {
				"id": "0",
				"members": [
					{
						"id": "2401",
						"type": {
							"displayName": "SLT",
							"carriages": 4,
							"reversalDuration": "0",
							"length": 69.36,
							"combineDuration": "180",
							"splitDuration": "120",
							"backNormTime": "120",
							"backAdditionTime": "16"
						}
					}
				],
				"parentIDs": [],
				"childIDs": [],
				"standingType": ""
			},
			"location": "41",
			"resources": [
				{
					"name": "47",
					"trackPartId": "47"
				}
			],
			"trainUnitIds": []
		},
		{
			"startTime": "3600",
			"endTime": "3870",
			"taskType": {
				"predefined": "Move"
			},
			"shuntingUnit": {
				"id": "1",
				"members": [
					{
						"id": "2402",
						"type": {
							"displayName": "SLT",
							"carriages": 4,
							"reversalDuration": "0",
							"length": 69.36,
							"combineDuration": "180",
							"splitDuration": "120",
							"backNormTime": "120",
							"backAdditionTime": "16"
						}
					},
					{
						"id": "2403",
						"type": {
							"displayName": "SLT",
							"carriages": 4,
							"reversalDuration": "0",
							"length": 69.36,
							"combineDuration": "180",
							"splitDuration": "120",
							"backNormTime": "120",
							"backAdditionTime": "16"
						}
					}
				],
				"parentIDs": [],
				"childIDs": [],
				"standingType": ""
			},
			"location": "10",
			"resources": [
				{
					"name": "68",
					"trackPartId": "68"
				},
				{
					"name": "32",
					"trackPartId": "32"
				},
				{
					"name": "49",
					"trackPartId": "49"
				},
				{
					"name": "33",
					"trackPartId": "33"
				},
				{
					"name": "69",
					"trackPartId": "69"
				},
				{
					"name": "27",
					"trackPartId": "27"
				},
				{
					"name": "67",
					"trackPartId": "67"
				},
				{
					"name": "8",
					"trackPartId": "8"
				}
			],
			"trainUnitIds": []
		},
		{
			"startTime": "3180",
			"endTime": "3600",
			"taskType": {
				"predefined": "Wait"
			},
			"shuntingUnit": {
				"id": "1",
				"members": [
					{
						"id": "2402",
						"type": {
							"displayName": "SLT",
							"carriages": 4,
							"reversalDuration": "0",
							"length": 69.36,
							"combineDuration": "180",
							"splitDuration": "120",
							"backNormTime": "120",
							"backAdditionTime": "16"
						}
					},
					{
						"id": "2403",
						"type": {
							"displayName": "SLT",
							"carriages": 4,
							"reversalDuration": "0",
							"length": 69.36,
							"combineDuration": "180",
							"splitDuration": "120",
							"backNormTime": "120",
							"backAdditionTime": "16"
						}
					}
				],
				"parentIDs": [],
				"childIDs": [],
				"standingType": ""
			},
			"location": "10",
			"resources": [],
			"trainUnitIds": []
		},
		{
			"startTime": "2580",
			"endTime": "3180",
			"taskType": {
				"other": "Reinigingsperron"
			},
			"shuntingUnit": {
				"id": "1",
				"members": [
					{
						"id": "2402",
						"type": {
							"displayName": "SLT",
							"carriages": 4,
							"reversalDuration": "0",
							"length": 69.36,
							"combineDuration": "180",
							"splitDuration": "120",
							"backNormTime": "120",
							"backAdditionTime": "16"
						}
					},
					{
						"id": "2403",
						"type": {
							"displayName": "SLT",
							"carriages": 4,
							"reversalDuration": "0",
							"length": 69.36,
							"combineDuration": "180",
							"splitDuration": "120",
							"backNormTime": "120",
							"backAdditionTime": "16"
						}
					}
				],
				"parentIDs": [],
				"childIDs": [],
				"standingType": ""
			},
			"location": "10",
			"resources": [
				{
					"name": "72",
					"facilityId": "72"
				}
			],
			"trainUnitIds": []
		},
		{
			"startTime": "900",
			"endTime": "3900",
			"taskType": {
				"predefined": "Wait"
			},
			"shuntingUnit": {
				"id": "2",
				"members": [
					{
						"id": "2404",
						"type": {
							"displayName": "SLT",
							"carriages": 4,
							"reversalDuration": "0",
							"length": 69.36,
							"combineDuration": "180",
							"splitDuration": "120",
							"backNormTime": "120",
							"backAdditionTime": "16"
						}
					}
				],
				"parentIDs": [],
				"childIDs": [],
				"standingType": ""
			},
			"location": "41",
			"resources": [],
			"trainUnitIds": []
		},
		{
			"startTime": "3900",
			"endTime": "3900",
			"taskType": {
				"predefined": "Move"
			},
			"shuntingUnit": {
				"id": "2",
				"members": [
					{
						"id": "2404",
						"type": {
							"displayName": "SLT",
							"carriages": 4,
							"reversalDuration": "0",
							"length": 69.36,
							"combineDuration": "180",
							"splitDuration": "120",
							"backNormTime": "120",
							"backAdditionTime": "16"
						}
					}
				],
				"parentIDs": [],
				"childIDs": [],
				"standingType": ""
			},
			"location": "41",
			"resources": [],
			"trainUnitIds": []
		},
		{
			"startTime": "3900",
			"endTime": "3900",
			"taskType": {
				"predefined": "Exit"
			},
			"shuntingUnit": {
				"id": "2",
				"members": [
					{
						"id": "2404",
						"type": {
							"displayName": "SLT",
							"carriages": 4,
							"reversalDuration": "0",
							"length": 69.36,
							"combineDuration": "180",
							"splitDuration": "120",
							"backNormTime": "120",
							"backAdditionTime": "16"
						}
					}
				],
				"parentIDs": [],
				"childIDs": [],
				"standingType": ""
			},
			"location": "41",
			"resources": [
				{
					"name": "47",
					"trackPartId": "47"
				}
			],
			"trainUnitIds": []
		},
		{
			"startTime": "3870",
			"endTime": "3900",
			"taskType": {
				"predefined": "Wait"
			},
			"shuntingUnit": {
				"id": "1",
				"members": [
					{
						"id": "2402",
						"type": {
							"displayName": "SLT",
							"carriages": 4,
							"reversalDuration": "0",
							"length": 69.36,
							"combineDuration": "180",
							"splitDuration": "120",
							"backNormTime": "120",
							"backAdditionTime": "16"
						}
					},
					{
						"id": "2403",
						"type": {
							"displayName": "SLT",
							"carriages": 4,
							"reversalDuration": "0",
							"length": 69.36,
							"combineDuration": "180",
							"splitDuration": "120",
							"backNormTime": "120",
							"backAdditionTime": "16"
						}
					}
				],
				"parentIDs": [],
				"childIDs": [],
				"standingType": ""
			},
			"location": "8",
			"resources": [],
			"trainUnitIds": []
		},
		{
			"startTime": "3900",
			"endTime": "4200",
			"taskType": {
				"predefined": "Move"
			},
			"shuntingUnit": {
				"id": "1",
				"members": [
					{
						"id": "2402",
						"type": {
							"displayName": "SLT",
							"carriages": 4,
							"reversalDuration": "0",
							"length": 69.36,
							"combineDuration": "180",
							"splitDuration": "120",
							"backNormTime": "120",
							"backAdditionTime": "16"
						}
					},
					{
						"id": "2403",
						"type": {
							"displayName": "SLT",
							"carriages": 4,
							"reversalDuration": "0",
							"length": 69.36,
							"combineDuration": "180",
							"splitDuration": "120",
							"backNormTime": "120",
							"backAdditionTime": "16"
						}
					}
				],
				"parentIDs": [],
				"childIDs": [],
				"standingType": ""
			},
			"location": "8",
			"resources": [
				{
					"name": "66",
					"trackPartId": "66"
				},
				{
					"name": "21",
					"trackPartId": "21"
				},
				{
					"name": "55",
					"trackPartId": "55"
				},
				{
					"name": "20",
					"trackPartId": "20"
				},
				{
					"name": "56",
					"trackPartId": "56"
				},
				{
					"name": "22",
					"trackPartId": "22"
				},
				{
					"name": "57",
					"trackPartId": "57"
				},
				{
					"name": "23",
					"trackPartId": "23"
				},
				{
					"name": "58",
					"trackPartId": "58"
				},
				{
					"name": "24",
					"trackPartId": "24"
				},
				{
					"name": "59",
					"trackPartId": "59"
				},
				{
					"name": "41",
					"trackPartId": "41"
				}
			],
			"trainUnitIds": []
		},
		{
			"startTime": "4200",
			"endTime": "4200",
			"taskType": {
				"predefined": "Exit"
			},
			"shuntingUnit": {
				"id": "1",
				"members": [
					{
						"id": "2402",
						"type": {
							"displayName": "SLT",
							"carriages": 4,
							"reversalDuration": "0",
							"length": 69.36,
							"combineDuration": "180",
							"splitDuration": "120",
							"backNormTime": "120",
							"backAdditionTime": "16"
						}
					},
					{
						"id": "2403",
						"type": {
							"displayName": "SLT",
							"carriages": 4,
							"reversalDuration": "0",
							"length": 69.36,
							"combineDuration": "180",
							"splitDuration": "120",
							"backNormTime": "120",
							"backAdditionTime": "16"
						}
					}
				],
				"parentIDs": [],
				"childIDs": [],
				"standingType": ""
			},
			"location": "41",
			"resources": [
				{
					"name": "47",
					"trackPartId": "47"
				}
			],
			"trainUnitIds": []
		}
	],
	"trackParts": []
}